MANIFEST.in
README.txt
bootstrap.py
buildout.cfg
setup.py
test-plone-3.3.x.cfg
test-plone-4.2.x.cfg
test-plone-4.3.x.cfg
tox.ini
Products/__init__.py
Products.Reflecto.egg-info/PKG-INFO
Products.Reflecto.egg-info/SOURCES.txt
Products.Reflecto.egg-info/dependency_links.txt
Products.Reflecto.egg-info/namespace_packages.txt
Products.Reflecto.egg-info/not-zip-safe
Products.Reflecto.egg-info/requires.txt
Products.Reflecto.egg-info/top_level.txt
Products/Reflecto/__init__.py
Products/Reflecto/catalog.py
Products/Reflecto/config.py
Products/Reflecto/configure.zcml
Products/Reflecto/events.py
Products/Reflecto/events.zcml
Products/Reflecto/fields.py
Products/Reflecto/interfaces.py
Products/Reflecto/permissions.py
Products/Reflecto/streaming.py
Products/Reflecto/utils.py
Products/Reflecto/uuids.py
Products/Reflecto/validators.py
Products/Reflecto/version.txt
Products/Reflecto/browser/__init__.py
Products/Reflecto/browser/adddirectory.py
Products/Reflecto/browser/addfile.py
Products/Reflecto/browser/configure.zcml
Products/Reflecto/browser/contents.py
Products/Reflecto/browser/download.py
Products/Reflecto/browser/index.py
Products/Reflecto/chardet/__init__.py
Products/Reflecto/chardet/big5freq.py
Products/Reflecto/chardet/big5prober.py
Products/Reflecto/chardet/chardistribution.py
Products/Reflecto/chardet/charsetgroupprober.py
Products/Reflecto/chardet/charsetprober.py
Products/Reflecto/chardet/codingstatemachine.py
Products/Reflecto/chardet/constants.py
Products/Reflecto/chardet/escprober.py
Products/Reflecto/chardet/escsm.py
Products/Reflecto/chardet/eucjpprober.py
Products/Reflecto/chardet/euckrfreq.py
Products/Reflecto/chardet/euckrprober.py
Products/Reflecto/chardet/euctwfreq.py
Products/Reflecto/chardet/euctwprober.py
Products/Reflecto/chardet/gb2312freq.py
Products/Reflecto/chardet/gb2312prober.py
Products/Reflecto/chardet/hebrewprober.py
Products/Reflecto/chardet/jisfreq.py
Products/Reflecto/chardet/jpcntx.py
Products/Reflecto/chardet/langbulgarianmodel.py
Products/Reflecto/chardet/langcyrillicmodel.py
Products/Reflecto/chardet/langgreekmodel.py
Products/Reflecto/chardet/langhebrewmodel.py
Products/Reflecto/chardet/langhungarianmodel.py
Products/Reflecto/chardet/langthaimodel.py
Products/Reflecto/chardet/latin1prober.py
