Metadata-Version: 1.1
Name: Products.Reflecto
Version: 3.0.6
Summary: Access the filesystem from Plone
Home-page: UNKNOWN
Author: Jarn AS
Author-email: support@jarn.com
License: GPL
Keywords: plone filesystem
Platform: UNKNOWN
Classifier: Framework :: Plone :: 3.3
Classifier: Framework :: Plone :: 4.0
Classifier: Framework :: Plone :: 4.1
Classifier: Framework :: Plone :: 4.2
Classifier: Programming Language :: Python
Classifier: Topic :: Software Development :: Libraries :: Python Modules
